tabarnak/__init__.py
tabarnak/tabarnak.py
tests/__init__.py
tests/config.py
tests/test_bat.py
tests/test_case_base.py
tests/test_codecs.py
tests/test_config.py
tests/test_fat.py
tabarnak_desjare-0.0.7.dist-info/LICENSE
tabarnak_desjare-0.0.7.dist-info/METADATA
tabarnak_desjare-0.0.7.dist-info/WHEEL
tabarnak_desjare-0.0.7.dist-info/entry_points.txt
tabarnak_desjare-0.0.7.dist-info/top_level.txt
tabarnak_desjare-0.0.7.dist-info/RECORD
