Metadata-Version: 2.1
Name: tabarnak-desjare
Version: 0.0.7
Summary: transcoder FFmpeg based wrapper
Home-page: https://github.com/desjare/tabarnak
Author: Eric Desjardins
Author-email: desjare@gmail.com
License: UNKNOWN
Platform: UNKNOWN
Classifier: Programming Language :: Python :: 3
Classifier: License :: OSI Approved :: GNU Lesser General Public License v2 or later (LGPLv2+)
Classifier: Operating System :: OS Independent
Classifier: Development Status :: 2 - Pre-Alpha
Classifier: Environment :: Console
Requires-Python: >=3.7
Requires-Dist: PyYAML
